pyrhapsody/__init__.py
pyrhapsody-1.0.0.dist-info/DESCRIPTION.rst
pyrhapsody-1.0.0.dist-info/METADATA
pyrhapsody-1.0.0.dist-info/RECORD
pyrhapsody-1.0.0.dist-info/WHEEL
pyrhapsody-1.0.0.dist-info/metadata.json
pyrhapsody-1.0.0.dist-info/pbr.json
pyrhapsody-1.0.0.dist-info/top_level.txt
