Metadata-Version: 2.0
Name: pyrhapsody
Version: 1.0.0
Summary: A simple Python wrapper for Rhapsody's V2 API
Home-page: https://github.com/rcrdclub/pyrhapsody
Author: Hery Ratsimihah
Author-email: UNKNOWN
License: MIT
Keywords: rhapsody api library
Platform: UNKNOWN
Classifier: Development Status :: 4 - Beta
Classifier: Intended Audience :: Developers
Classifier: Natural Language :: English
Classifier: License :: OSI Approved :: MIT License
Classifier: Programming Language :: Python :: 2.7
Requires-Dist: requests
